catpic/__init__.py
catpic/basis_aspect_system.py
catpic/cli.py
catpic/cli_auto_detect.py
catpic/config.py
catpic/core.py
catpic/decoder.py
catpic/detection.py
catpic/encoder.py
catpic/encoder_layers.py
catpic/encoder_melding.py
catpic/framebuffer.py
catpic/geometry.py
catpic/meow_parser.py
catpic/primitives.py
catpic/py.typed
catpic/renderer.py
catpic/protocols/__init__.py
catpic/protocols/base.py
catpic/protocols/base_modifications.py
catpic/protocols/core.py
catpic/protocols/glyxel.py
catpic/protocols/glyxel_clear_method.py
catpic/protocols/iterm2.py
catpic/protocols/kitty.py
catpic/protocols/sixel.py
catpic/IMPLEMENTATION.md
catpic/docs/api-reference.md
catpic/docs/getting-started.md
catpic/docs/index.md
catpic/docs/primitives_api.md
catpic/docs/implementations/c.md
catpic/docs/implementations/python.md
catpic/spec/api.md
catpic/spec/compliance.md
catpic/spec/meow_format.md
catpic/spec/protocol.md
catpic/spec/test-vectors.json
catpic-0.9.0.dist-info/METADATA
catpic-0.9.0.dist-info/WHEEL
catpic-0.9.0.dist-info/entry_points.txt
catpic-0.9.0.dist-info/RECORD
