Metadata-Version: 2.4
Name: catpic
Version: 0.9.0
Summary: Display images in terminals using Unicode mosaics and ANSI colors
Project-URL: Homepage, https://github.com/friscorose/catpic
Project-URL: Repository, https://github.com/friscorose/catpic
Project-URL: Issues, https://github.com/friscorose/catpic/issues
Project-URL: Documentation, https://github.com/friscorose/catpic/tree/main/docs
Author-email: Frisco Rose <friscorose@gmail.com>
License: MIT
Keywords: ansi,ascii,image,meow,mosaic,terminal,tui,unicode
Classifier: Development Status :: 4 - Beta
Classifier: Environment :: Console
Classifier: Intended Audience :: Developers
Classifier: Intended Audience :: End Users/Desktop
Classifier: License :: OSI Approved :: MIT License
Classifier: Operating System :: OS Independent
Classifier: Programming Language :: Python :: 3
Classifier: Programming Language :: Python :: 3.9
Classifier: Programming Language :: Python :: 3.10
Classifier: Programming Language :: Python :: 3.11
Classifier: Programming Language :: Python :: 3.12
Classifier: Topic :: Multimedia :: Graphics :: Graphics Conversion
Classifier: Topic :: Multimedia :: Graphics :: Viewers
Classifier: Topic :: System :: Shells
Classifier: Topic :: Terminals
Requires-Python: >=3.9
Requires-Dist: click>=8.0.0
Requires-Dist: pillow>=9.0.0
Provides-Extra: dev
Requires-Dist: black>=23.0.0; extra == 'dev'
Requires-Dist: mypy>=1.5.0; extra == 'dev'
Requires-Dist: pytest-cov>=4.0.0; extra == 'dev'
Requires-Dist: pytest>=8.3.5; extra == 'dev'
Requires-Dist: ruff>=0.1.0; extra == 'dev'
Requires-Dist: types-pillow; extra == 'dev'
